bridge/__init__.py
tnsp_bridge-0.3.17.dist-info/METADATA
tnsp_bridge-0.3.17.dist-info/WHEEL
tnsp_bridge-0.3.17.dist-info/top_level.txt
tnsp_bridge-0.3.17.dist-info/RECORD
