Metadata-Version: 2.1
Name: tnsp_bridge
Version: 0.3.17
Summary: bridge from TNSP to TAT
Author-email: Hao Zhang <zh970205@mail.ustc.edu.cn>
License: GPLv3
Project-URL: Homepage, https://github.com/USTC-TNS/TNSP/tree/main/tnsp_bridge
Project-URL: Repository, https://github.com/USTC-TNS/TNSP.git
Project-URL: Issues, https://github.com/USTC-TNS/TNSP/issues
Project-URL: Changelog, https://github.com/USTC-TNS/TNSP/blob/main/CHANGELOG.org
Keywords: tensor,tensor network,tensor network state,PEPS,MPS,quantum many body system
Classifier: Development Status :: 4 - Beta
Classifier: Programming Language :: Python :: 3
Classifier: License :: OSI Approved :: GNU General Public License v3 or later (GPLv3+)
Classifier: Topic :: Scientific/Engineering :: Mathematics
Classifier: Topic :: Scientific/Engineering :: Physics
Classifier: Topic :: Software Development :: Libraries :: Python Modules
Requires-Python: >=3.7
Requires-Dist: pytat==0.3.17
